ddtcurve/__init__.py
ddtcurve/cal.py
ddtcurve/infer.py
ddtcurve-0.2.1.dist-info/LICENSE
ddtcurve-0.2.1.dist-info/METADATA
ddtcurve-0.2.1.dist-info/WHEEL
ddtcurve-0.2.1.dist-info/top_level.txt
ddtcurve-0.2.1.dist-info/RECORD
