Metadata-Version: 2.1
Name: ddtcurve
Version: 0.2.1
Summary: A package used to calculate the strength of the ddtank game.
Author-email: zx <jugking6688@gmail.com>
Classifier: Programming Language :: Python :: 3
Classifier: License :: OSI Approved :: MIT License
Classifier: Operating System :: OS Independent
Requires-Python: >=3.8
License-File: LICENSE
Requires-Dist: numpy
Requires-Dist: scipy
Requires-Dist: onnxruntime ~=1.17.0
